LICENSE.txt
MANIFEST.in
README.md
requirements.txt
setup.py
docs/Makefile
docs/dashbuild.py
docs/requirements.txt
docs/source/conf.py
docs/source/index.rst
docs/source/packing_big.rst
docs/source/packing_little.rst
pcstools/__init__.py
pcstools/compat.py
pcstools.egg-info/PKG-INFO
pcstools.egg-info/SOURCES.txt
pcstools.egg-info/dependency_links.txt
pcstools.egg-info/top_level.txt
pcstools/packing/__init__.py
pcstools/packing/big_endian.py
pcstools/packing/little_endian.py