Metadata-Version: 1.2
Name: pcstools
Version: 0.3
Summary: Tools for the course Proactive Computer Security at DIKU
Home-page: https://github.com/DIKU-PCS/pcstools
Author: Mathias Svensson
Author-email: freaken@freaken.dk
License: MIT
Platform: UNKNOWN
Classifier: Intended Audience :: Developers
Classifier: Intended Audience :: Science/Research
Classifier: Intended Audience :: System Administrators
Classifier: License :: OSI Approved :: MIT License
Classifier: Natural Language :: English
Classifier: Operating System :: POSIX :: Linux
Classifier: Programming Language :: Python :: 2.7
Classifier: Topic :: Security
Classifier: Topic :: Software Development :: Libraries :: Python Modules
Classifier: Topic :: Utilities
Requires-Python: >=2.7, !=3.0.*, !=3.1.*, !=3.2.*, <4
